{"background_harmonic_balance.md":"D5j6qEu-","background_limit_cycles.md":"CIO2kf27","background_stability_response.md":"D1xdAek2","examples_ab_initio_noise.md":"Bh7LJDS7","examples_cumulants_kpo.md":"te7pQ6nO","examples_harmonic_oscillator_kb_vs_hb.md":"D-sUtz-P","examples_index.md":"BXGGP306","examples_parametric_via_three_wave_mixing.md":"DMjujReq","examples_parametron.md":"jVjxGNF2","examples_state_dependent_perturbation.md":"B1_Rug3c","examples_steady_state_sweep.md":"7_yxtv12","examples_wave_mixing.md":"BZ_eZfVm","index.md":"z2GcRwec","introduction_citation.md":"Pt3r6buB","introduction_index.md":"B-T2_mrU","manual_analyse_solutions.md":"Dpz9Pp-n","manual_api.md":"Ix2eJsxr","manual_entering_eom.md":"DgdZmISv","manual_extracting_harmonics.md":"D13r2FsN","manual_linear_response.md":"DBsdQ9X8","manual_methods.md":"C_G6Wv9b","manual_plotting.md":"CUyaTJBv","manual_scimlext.md":"DbBOmaSf","manual_solving_harmonics.md":"Bo_mudWd","manual_time_dependent.md":"Bk8G9ZDT","tutorials_classification.md":"Dh0va3k7","tutorials_index.md":"BYIc3Ghl","tutorials_limit_cycles.md":"CWTXGj0I","tutorials_linear_response.md":"DTqJk6jc","tutorials_steady_states.md":"BYH3mKz4","tutorials_time_dependent.md":"D_r5QalM"}
