{"background_harmonic_balance.md":"Bz9q0QGb","background_limit_cycles.md":"Borsi4z1","background_stability_response.md":"BJaKetlE","examples_ab_initio_noise.md":"LpHb_KUX","examples_cumulants_kpo.md":"DisYREfO","examples_forward_transmission.md":"CMLeUgBb","examples_harmonic_oscillator_kb_vs_hb.md":"Do8cwpqm","examples_index.md":"HJCTSqtZ","examples_parametric_via_three_wave_mixing.md":"ODeJbql0","examples_parametron.md":"D1RVGIFK","examples_state_dependent_perturbation.md":"8q24kEZW","examples_steady_state_sweep.md":"N_w7PdvW","examples_wave_mixing.md":"CeT7hd82","index.md":"D0icenOW","introduction_citation.md":"DTzlBbn_","introduction_index.md":"CvCkuEqu","manual_analyse_solutions.md":"DUFXEVU4","manual_api.md":"Dop9dToc","manual_entering_eom.md":"DiLUU1Y0","manual_extracting_harmonics.md":"cKPB7r4u","manual_linear_response.md":"3uVBmq90","manual_methods.md":"C3d_sc1z","manual_plotting.md":"De64kfgO","manual_scimlext.md":"h-vYmz3s","manual_solving_harmonics.md":"Gng-FCLr","manual_time_dependent.md":"DXnBFjTG","tutorials_classification.md":"gioEJvld","tutorials_index.md":"KzTCgfGY","tutorials_limit_cycles.md":"BKb-yeZU","tutorials_linear_response.md":"CS5SCH-R","tutorials_steady_states.md":"D74jvE4b","tutorials_time_dependent.md":"CPue4B7K"}
