{"background_harmonic_balance.md":"BPs-ERXZ","background_limit_cycles.md":"C1n6gfiB","background_stability_response.md":"Di2TOVl2","examples_ab_initio_noise.md":"bSpeBvPH","examples_cumulants_kpo.md":"kHxFkcZA","examples_forward_transmission.md":"C0DdS48V","examples_harmonic_oscillator_kb_vs_hb.md":"CxKLWTnc","examples_index.md":"BbIU-Vt2","examples_parametric_via_three_wave_mixing.md":"CsRV3Fsp","examples_parametron.md":"BDiHVr-c","examples_state_dependent_perturbation.md":"D1WJcEb3","examples_steady_state_sweep.md":"B_ZAn92a","examples_wave_mixing.md":"C-RQVDUO","index.md":"4UWC6bQA","introduction_citation.md":"CPXGDVRK","introduction_index.md":"DdSVQTaC","manual_analyse_solutions.md":"CWYx3j0h","manual_api.md":"BX3_Jrgf","manual_entering_eom.md":"B2UD5GYK","manual_extracting_harmonics.md":"DOviZ2Vk","manual_linear_response.md":"Ctrnz8Oe","manual_methods.md":"BPRKZ_MT","manual_plotting.md":"DsqHHUIl","manual_scimlext.md":"C1VxnTGg","manual_solving_harmonics.md":"DIcgeNGm","manual_time_dependent.md":"h6Gt14iI","tutorials_classification.md":"dR9s4Bee","tutorials_index.md":"KIbCpDLq","tutorials_limit_cycles.md":"DEu0-BIa","tutorials_linear_response.md":"BNCcgFdg","tutorials_steady_states.md":"33t6s4A_","tutorials_time_dependent.md":"Dc_EhLnu"}
